WinColors/__init__.py
python_colors_windows-1.0.dist-info/LICENSE
python_colors_windows-1.0.dist-info/METADATA
python_colors_windows-1.0.dist-info/WHEEL
python_colors_windows-1.0.dist-info/top_level.txt
python_colors_windows-1.0.dist-info/RECORD
