Metadata-Version: 2.1
Name: python-colors-windows
Version: 1.0
Summary: Python-Colors-Windows is used for Beautify Your Output With Just calling a function
Home-page: https://github.com/pmk456/python-colors-windows
Author: Patan Musthakheem
Author-email: patanmusthakheem786@gmail.com
License: UNKNOWN
Project-URL: Bug Tracker, https://github.com/pmk456/python-colors-windows/issues
Platform: UNKNOWN
Classifier: Programming Language :: Python :: 3
Classifier: License :: OSI Approved :: Apache Software License
Classifier: Operating System :: OS Independent
Requires-Python: >=3.0
License-File: LICENSE
